reyan/__init__.py
reyan/checkSac.py
reyan/sac.py
reyan-0.0.57.dist-info/METADATA
reyan-0.0.57.dist-info/WHEEL
reyan-0.0.57.dist-info/entry_points.txt
reyan-0.0.57.dist-info/top_level.txt
reyan-0.0.57.dist-info/RECORD
