Metadata-Version: 2.1
Name: reyan
Version: 0.0.57
Summary: reyan.
Home-page: https://github.com/r-e-y-a-n/reyan-pip
Author: reyan
